setup.cfg
setup.py
sysfs/__init__.py
sysfs/gpio.py
sysfs_gpio.egg-info/PKG-INFO
sysfs_gpio.egg-info/SOURCES.txt
sysfs_gpio.egg-info/dependency_links.txt
sysfs_gpio.egg-info/requires.txt
sysfs_gpio.egg-info/top_level.txt