Metadata-Version: 1.0
Name: sysfs-gpio
Version: 0.2.2
Summary: Linux SysFS GPIO Access
Home-page: http://derekstavis.github.io
Author: Derek Willian Stavis
Author-email: dekestavis@gmail.com
License: UNKNOWN
Platform: UNKNOWN
